krypton_ml/__init__.py
krypton_ml/core/__init__.py
krypton_ml/core/loader/__init__.py
krypton_ml/core/loader/config.py
krypton_ml/core/loader/module.py
krypton_ml/core/models/__init__.py
krypton_ml/core/models/cli_config.py
krypton_ml/core/models/registry.py
krypton_ml/core/registry/__init__.py
krypton_ml/core/registry/model_registry.py
krypton_ml/core/runtime/__init__.py
krypton_ml/core/runtime/hugging_face.py
krypton_ml/core/utils/__init__.py
krypton_ml/core/utils/logger.py
krypton_ml/core/webserver/__init__.py
krypton_ml/core/webserver/log_middleware.py
krypton_ml/core/webserver/model_endpoints.py
krypton_ml/core/webserver/server_runtime.py
krypton_ml/main.py
krypton_ml-0.1.8.dist-info/LICENSE
krypton_ml-0.1.8.dist-info/METADATA
krypton_ml-0.1.8.dist-info/WHEEL
krypton_ml-0.1.8.dist-info/entry_points.txt
krypton_ml-0.1.8.dist-info/RECORD
