Metadata-Version: 2.1
Name: krypton-ml
Version: 0.1.8
Summary: A ML model serving library
Home-page: https://github.com/kryptonhq/krypton-ml
License: MIT
Author: Varun Kruthiventi
Requires-Python: >=3.9,<4.0
Classifier: License :: OSI Approved :: MIT License
Classifier: Operating System :: OS Independent
Classifier: Programming Language :: Python :: 3
Classifier: Programming Language :: Python :: 3.9
Classifier: Programming Language :: Python :: 3.10
Classifier: Programming Language :: Python :: 3.11
Classifier: Programming Language :: Python :: 3.12
Classifier: Programming Language :: Python :: 3.13
Requires-Dist: fastapi[standard] (>=0.115.0,<0.116.0)
Requires-Dist: langchain (>=0.3.1,<0.4.0)
Requires-Dist: pydantic (>=2.9.2,<3.0.0)
Requires-Dist: pydantic-yaml (>=1.3.0,<2.0.0)
Requires-Dist: transformers[torch] (>=4.47.0,<5.0.0)
Requires-Dist: typer (>=0.12.5,<0.13.0)
Project-URL: Repository, https://github.com/kryptonhq/krypton-ml
